PeeweeExtraFields/PasswordFields.py
PeeweeExtraFields/TechFields.py
PeeweeExtraFields/__init__.py
tests/__init__.py
tests/test_fields.py
PeeweeExtraFields-0.0.5.dist-info/LICENSE
PeeweeExtraFields-0.0.5.dist-info/METADATA
PeeweeExtraFields-0.0.5.dist-info/WHEEL
PeeweeExtraFields-0.0.5.dist-info/top_level.txt
PeeweeExtraFields-0.0.5.dist-info/RECORD
