Metadata-Version: 2.1
Name: PeeweeExtraFields
Version: 0.0.5
Summary: Collection of Extra Fields for peewee ORM.
Home-page: https://github.com/YADRO-KNS/PeeweeExtraFields
Author: Sergey Parshin
Author-email: parshinsp@gmail.com
License: UNKNOWN
Platform: UNKNOWN
Classifier: Development Status :: 4 - Beta
Classifier: Programming Language :: Python :: 3.6
Classifier: Programming Language :: Python :: 3.7
Classifier: Programming Language :: Python :: 3.8
Classifier: License :: OSI Approved :: MIT License
Classifier: Operating System :: OS Independent
Requires-Dist: peewee (>=3.9.6)
